compspec/__init__.py
compspec/entity.py
compspec/graph.py
compspec/logger.py
compspec/schema.py
compspec/solver.py
compspec/utils.py
compspec/version.py
compspec/asp/__init__.py
compspec/asp/base.py
compspec/asp/combination.py
compspec/asp/composition.py
compspec/asp/diff.py
compspec/asp/lp/__init__.py
compspec/asp/lp/is-compatible.lp
compspec/cli/__init__.py
compspec/cli/extract.py
compspec/create/__init__.py
compspec/create/artifact.py
compspec/create/jsongraph.py
compspec/plugin/__init__.py
compspec/plugin/parser.py
compspec/plugin/plugin.py
compspec/plugin/registry.py
compspec-0.1.15.dist-info/LICENSE
compspec-0.1.15.dist-info/METADATA
compspec-0.1.15.dist-info/NOTICE
compspec-0.1.15.dist-info/WHEEL
compspec-0.1.15.dist-info/entry_points.txt
compspec-0.1.15.dist-info/top_level.txt
compspec-0.1.15.dist-info/RECORD
