Metadata-Version: 2.1
Name: compspec
Version: 0.1.15
Summary: Compatibility specifications and models
Home-page: https://github.com/compspec/compspec
Author: Vanessa Sochat
Author-email: vsoch@users.noreply.github.com
Maintainer: Vanessa Sochat
License: LICENSE
Keywords: diff,comparison,composition,specification,abi,compatibility,symbols
Classifier: Intended Audience :: Science/Research
Classifier: Intended Audience :: Developers
Classifier: License :: OSI Approved :: Mozilla Public License 2.0 (MPL 2.0)
Classifier: Programming Language :: C
Classifier: Programming Language :: Python
Classifier: Topic :: Software Development
Classifier: Topic :: Scientific/Engineering
Classifier: Operating System :: Unix
Classifier: Programming Language :: Python :: 3.3
License-File: LICENSE
License-File: NOTICE
Requires-Dist: clingo
Requires-Dist: pyaml
Requires-Dist: jsonschema
Requires-Dist: requests
Requires-Dist: argparse-dataclass
Provides-Extra: all
Requires-Dist: clingo ; extra == 'all'
Requires-Dist: pyaml ; extra == 'all'
Requires-Dist: jsonschema ; extra == 'all'
Requires-Dist: requests ; extra == 'all'
Requires-Dist: argparse-dataclass ; extra == 'all'
Requires-Dist: pytest >=4.6.2 ; extra == 'all'
